AUTHORS
COPYING
ChangeLog
MANIFEST.in
README.rst
fetch-messages
imap-folders
imap-purge
imap-stats
process-messages
setup.py
store-message
IMAPUtils/Codec.py
IMAPUtils/__init__.py
imap_utils.egg-info/PKG-INFO
imap_utils.egg-info/SOURCES.txt
imap_utils.egg-info/dependency_links.txt
imap_utils.egg-info/top_level.txt