Metadata-Version: 1.1
Name: imap-utils
Version: 0.5
Summary: IMAP utils
Home-page: http://cihar.com/software/imap-utils/
Author: Michal Čihař
Author-email: michal@cihar.com
License: GPL
Download-URL: http://cihar.com/software/imap-utils/
Keywords: IMAP,mail,email
Platform: Linux
Platform: Mac OSX
Platform: Windows XP/2000/NT
Platform: Windows 95/98/ME
Classifier: Development Status :: 5 - Production/Stable
Classifier: Environment :: Console
Classifier: Intended Audience :: Developers
Classifier: Intended Audience :: System Administrators
Classifier: License :: OSI Approved :: GNU General Public License (GPL)
Classifier: Operating System :: OS Independent
Classifier: Programming Language :: Python
Classifier: Topic :: Communications :: Email
Classifier: Topic :: Utilities
